gapless_crypto_clickhouse/__init__.py
gapless_crypto_clickhouse/__probe__.py
gapless_crypto_clickhouse/api.py
gapless_crypto_clickhouse/cli.py
gapless_crypto_clickhouse/clickhouse_query.py
gapless_crypto_clickhouse/exceptions.py
gapless_crypto_clickhouse/llms.txt
gapless_crypto_clickhouse/probe.py
gapless_crypto_clickhouse/query_api.py
gapless_crypto_clickhouse/clickhouse/__init__.py
gapless_crypto_clickhouse/clickhouse/config.py
gapless_crypto_clickhouse/clickhouse/connection.py
gapless_crypto_clickhouse/clickhouse/schema.sql
gapless_crypto_clickhouse/clickhouse/schema_validator.py
gapless_crypto_clickhouse/collectors/__init__.py
gapless_crypto_clickhouse/collectors/binance_public_data_collector.py
gapless_crypto_clickhouse/collectors/clickhouse_bulk_loader.py
gapless_crypto_clickhouse/collectors/concurrent_collection_orchestrator.py
gapless_crypto_clickhouse/collectors/csv_format_detector.py
gapless_crypto_clickhouse/collectors/httpx_downloader.py
gapless_crypto_clickhouse/collectors/hybrid_url_generator.py
gapless_crypto_clickhouse/constants/__init__.py
gapless_crypto_clickhouse/constants/binance.py
gapless_crypto_clickhouse/constants/deployment.py
gapless_crypto_clickhouse/constants/network.py
gapless_crypto_clickhouse/constants/timeframes.py
gapless_crypto_clickhouse/gap_filling/__init__.py
gapless_crypto_clickhouse/gap_filling/rest_client.py
gapless_crypto_clickhouse/gap_filling/safe_file_operations.py
gapless_crypto_clickhouse/gap_filling/universal_gap_filler.py
gapless_crypto_clickhouse/resume/__init__.py
gapless_crypto_clickhouse/resume/intelligent_checkpointing.py
gapless_crypto_clickhouse/utils/__init__.py
gapless_crypto_clickhouse/utils/error_handling.py
gapless_crypto_clickhouse/utils/etag_cache.py
gapless_crypto_clickhouse/utils/timeframe_constants.py
gapless_crypto_clickhouse/utils/timestamp_format_analyzer.py
gapless_crypto_clickhouse/utils/timestamp_utils.py
gapless_crypto_clickhouse/validation/__init__.py
gapless_crypto_clickhouse-17.4.0.dist-info/METADATA
gapless_crypto_clickhouse-17.4.0.dist-info/WHEEL
gapless_crypto_clickhouse-17.4.0.dist-info/entry_points.txt
gapless_crypto_clickhouse-17.4.0.dist-info/licenses/LICENSE
gapless_crypto_clickhouse-17.4.0.dist-info/RECORD
