Metadata-Version: 2.4
Name: gapless-crypto-clickhouse
Version: 17.4.0
Summary: ClickHouse-based cryptocurrency data collection with zero-gap guarantee. 22x faster via Binance public repository with persistent database storage, USDT-margined futures support, and production-ready ReplacingMergeTree schema.
Project-URL: Homepage, https://github.com/terrylica/gapless-crypto-clickhouse
Project-URL: Documentation, https://github.com/terrylica/gapless-crypto-clickhouse#readme
Project-URL: Repository, https://github.com/terrylica/gapless-crypto-clickhouse.git
Project-URL: Issues, https://github.com/terrylica/gapless-crypto-clickhouse/issues
Project-URL: Changelog, https://github.com/terrylica/gapless-crypto-clickhouse/blob/main/CHANGELOG.md
Author-email: Eon Labs <terry@eonlabs.com>
Maintainer-email: Terry Li <terry@eonlabs.com>
License: MIT
License-File: LICENSE
Keywords: 22x-faster,OHLCV,USDT-margined,binance,clickhouse,crypto,cryptocurrency,data-warehouse,database,deterministic-versioning,financial-data,futures,gap-filling,gapless,liquidity,microstructure,order-flow,perpetual,persistent-storage,production-ready,replacing-mergetree,sql-queries,time-series,trading,zero-gaps
Classifier: Development Status :: 4 - Beta
Classifier: Intended Audience :: Developers
Classifier: Intended Audience :: Financial and Insurance Industry
Classifier: License :: OSI Approved :: MIT License
Classifier: Operating System :: OS Independent
Classifier: Programming Language :: Python :: 3
Classifier: Programming Language :: Python :: 3.11
Classifier: Programming Language :: Python :: 3.12
Classifier: Programming Language :: Python :: 3.13
Classifier: Topic :: Database
Classifier: Topic :: Office/Business :: Financial :: Investment
Classifier: Topic :: Scientific/Engineering :: Information Analysis
Classifier: Topic :: Software Development :: Libraries :: Python Modules
Requires-Python: >=3.11
Requires-Dist: binance-futures-availability>=1.4.0
Requires-Dist: click>=8.0.0
Requires-Dist: clickhouse-connect<1.0.0,>=0.10.0
Requires-Dist: duckdb>=1.1.0
Requires-Dist: httpx>=0.25.0
Requires-Dist: numpy<3.0.0,>=1.23.2
Requires-Dist: pandas<3.0.0,>=2.2.0
Requires-Dist: pyarrow>=14.0.0
Requires-Dist: pydantic>=2.0.0
Requires-Dist: requests>=2.31.0
Requires-Dist: tenacity>=8.0.0
